join_skew_data_p3/__init__.py
join_skew_data_p3/bin_packing_utils.py
join_skew_data_p3/join_skew_data.py
join_skew_data_p3-0.7.dist-info/LICENSE.txt
join_skew_data_p3-0.7.dist-info/METADATA
join_skew_data_p3-0.7.dist-info/WHEEL
join_skew_data_p3-0.7.dist-info/top_level.txt
join_skew_data_p3-0.7.dist-info/RECORD
