Metadata-Version: 2.1
Name: join-skew-data-p3
Version: 0.7
Summary: customize partitions with skew data for join
Home-page: https://github.com/ijan10/pyspark_handle_skewed_data
Author: itzik jan
Author-email: itzikjan@gmail.com
License: Undertone
Download-URL: https://github.com/ijan10/pyspark_handle_skewed_data/archive/v_0.5.tar.gz
Keywords: PySpark,skew,join
Platform: UNKNOWN
Classifier: Development Status :: 3 - Alpha
Classifier: Intended Audience :: Developers
Classifier: Topic :: Software Development :: Build Tools
Classifier: License :: OSI Approved :: MIT License
Classifier: Programming Language :: Python :: 3.8
